hippylib/__init__.py
hippylib/version.py
hippylib/algorithms/NewtonCG.py
hippylib/algorithms/__init__.py
hippylib/algorithms/bfgs.py
hippylib/algorithms/cgsampler.py
hippylib/algorithms/cgsolverSteihaug.py
hippylib/algorithms/linSolvers.py
hippylib/algorithms/linalg.py
hippylib/algorithms/lowRankOperator.py
hippylib/algorithms/multivector.py
hippylib/algorithms/randomizedEigensolver.py
hippylib/algorithms/randomizedSVD.py
hippylib/algorithms/snes.py
hippylib/algorithms/steepestDescent.py
hippylib/algorithms/traceEstimator.py
hippylib/algorithms/cpp_multivector/multivector.cpp
hippylib/algorithms/cpp_multivector/multivector.hpp
hippylib/forward_uq/__init__.py
hippylib/forward_uq/parameter2QoiMap.py
hippylib/forward_uq/qoi.py
hippylib/forward_uq/taylorApproximationQoi.py
hippylib/forward_uq/varianceReductionMC.py
hippylib/forward_uq/variationalQoi.py
hippylib/mcmc/__init__.py
hippylib/mcmc/chain.py
hippylib/mcmc/diagnostics.py
hippylib/mcmc/kernels.py
hippylib/mcmc/tracers.py
hippylib/modeling/PDEProblem.py
hippylib/modeling/PDEVariationalProblem.py
hippylib/modeling/SNES_TimeDependentVariationalProblem.py
hippylib/modeling/TimeDependentPDEVariationalProblem.py
hippylib/modeling/__init__.py
hippylib/modeling/expression.py
hippylib/modeling/misfit.py
hippylib/modeling/model.py
hippylib/modeling/modelVerify.py
hippylib/modeling/pointwiseObservation.py
hippylib/modeling/posterior.py
hippylib/modeling/prior.py
hippylib/modeling/reducedHessian.py
hippylib/modeling/timeDependentVector.py
hippylib/modeling/variables.py
hippylib/modeling/cpp_AssemblePointwiseObservation/AssemblePointwiseObservation.cpp
hippylib/modeling/cpp_AssemblePointwiseObservation/AssemblePointwiseObservation.h
hippylib/scheduling/__init__.py
hippylib/scheduling/collective.py
hippylib/test/__init__.py
hippylib/test/ptest_collectives.py
hippylib/test/ptest_multivector.py
hippylib/test/ptest_numpy2expression.py
hippylib/test/ptest_numpy2meshFunction.py
hippylib/test/ptest_pointwise_observation.py
hippylib-3.2.0.dist-info/METADATA
hippylib-3.2.0.dist-info/WHEEL
hippylib-3.2.0.dist-info/top_level.txt
hippylib-3.2.0.dist-info/RECORD
