Metadata-Version: 2.4
Name: hippylib
Version: 3.2.0
Summary: an Extensible Software Framework for Large-scale Deterministic and Bayesian Inverse Problems
Home-page: https://hippylib.github.io/
Author: Umberto Villa, Noemi Petra, Omar Ghattas
Author-email: uvilla@austin.utexas.edu
Project-URL: Bug Reports, https://github.com/hippylib/hippylib/issues
Project-URL: Source, https://github.com/hippylib/hippylib
Keywords: Infinite-dimensional inverse problems,adjoint-based methods,numerical optimization,low-rank approximation,Bayesian inference,uncertainty quantification,sampling
Classifier: Development Status :: 5 - Production/Stable
Classifier: Intended Audience :: Science/Research
Classifier: Topic :: Scientific/Engineering
Classifier: License :: OSI Approved :: GNU General Public License v2 (GPLv2)
Classifier: Programming Language :: Python :: 3
Classifier: Programming Language :: Python :: 3.6
Classifier: Programming Language :: Python :: 3.7
Requires-Python: >=3.6,<4
Requires-Dist: mpi4py
Requires-Dist: numpy
Requires-Dist: matplotlib
Requires-Dist: scipy
Provides-Extra: notebook
Requires-Dist: jupyter; extra == "notebook"
Dynamic: author
Dynamic: author-email
Dynamic: classifier
Dynamic: description
Dynamic: description-content-type
Dynamic: home-page
Dynamic: keywords
Dynamic: project-url
Dynamic: provides-extra
Dynamic: requires-dist
Dynamic: requires-python
Dynamic: summary
